ezlocalai/CTTS.py
ezlocalai/Embedding.py
ezlocalai/Helpers.py
ezlocalai/IMG.py
ezlocalai/LLM.py
ezlocalai/STT.py
ezlocalai/VLM.py
ezlocalai/__init__.py
ezlocalai-0.1.12.dist-info/LICENSE
ezlocalai-0.1.12.dist-info/METADATA
ezlocalai-0.1.12.dist-info/WHEEL
ezlocalai-0.1.12.dist-info/top_level.txt
ezlocalai-0.1.12.dist-info/RECORD
