Metadata-Version: 2.1
Name: ezlocalai
Version: 0.1.12
Summary: ezlocalai is an easy to set up local multimodal artificial intelligence server with OpenAI Style Endpoints.
Author: Josh XT
Author-email: josh@devxt.com
Requires-Python: >=3.10
License-File: LICENSE
Requires-Dist: spacy ==3.7.4
Requires-Dist: fastapi
Requires-Dist: uvicorn
Requires-Dist: streamlit
Requires-Dist: pydantic
Requires-Dist: requests ==2.32.0
Requires-Dist: tiktoken ==0.6.0
Requires-Dist: python-dotenv ==1.0.1
Requires-Dist: beautifulsoup4 ==4.12.3
Requires-Dist: faster-whisper ==1.0.2
Requires-Dist: pydub ==0.25.1
Requires-Dist: ffmpeg-python ==0.2.0
Requires-Dist: torch ==2.3.1
Requires-Dist: torchaudio ==2.3.1
Requires-Dist: transformers
Requires-Dist: TTS ==0.22.0
Requires-Dist: sounddevice ==0.4.6
Requires-Dist: pyaudio ==0.2.14
Requires-Dist: webrtcvad ==2.0.10
Requires-Dist: pyngrok ==7.1.6
Requires-Dist: accelerate
Requires-Dist: python-multipart
Requires-Dist: openai
Requires-Dist: pdfplumber
Requires-Dist: optimum
Requires-Dist: onnx
Requires-Dist: diffusers[torch]
Requires-Dist: llama-cpp-python ==0.2.82
